{"name":"Maltego Technologies","workspacecount":2,"icon":"https://www.maltego.com/img/Social%20Profile%20Pic@4x.png","description":"The official store for Kasm supported workspaces for Maltego Developers.","list_url":"https://rajacs50.github.io/kasm-registry/","contact_url":"https://github.com/rajacs50/kasm-registry/issues","modified":1721122563116,"workspaces":[{"description":"Chromium is a free and open-source browser, primarily developed and maintained by Google.","docker_registry":"https://index.docker.io/v1/","image_src":"chromium.png","name":"kasmweb/chromium:develop","run_config":{"hostname":"kasm"},"exec_config":{"go":{"cmd":"bash -c '/dockerstartup/custom_startup.sh --go --url \"$KASM_URL\"'"},"assign":{"cmd":"bash -c '/dockerstartup/custom_startup.sh --assign --url \"$KASM_URL\"'"}},"categories":["Browser"],"friendly_name":"Chromium","architecture":["amd64","arm64"],"compatibility":["1.13.x","1.14.x","1.15.x"],"uncompressed_size_mb":2170,"sha":"4d3cee5b47d70683376a717374745076ba17c9c7"},{"description":"Visual Studio Code is a code editor redefined and optimized for building and debugging modern web and cloud applications.","docker_registry":"https://index.docker.io/v1/","name":"kasmweb/vs-code:develop","image_src":"https://raw.githubusercontent.com/rajacs50/kasm-registry/1.0/workspaces/VSCode/vscode.png","categories":["Development"],"friendly_name":"Visual Studio Code","architecture":["amd64","arm64"],"compatibility":["1.13.x","1.14.x","1.15.x"],"uncompressed_size_mb":2170,"sha":"ff9ae6ecdce928eb427b7b3d637304d2e9bd0080"}]}